{
  "range": "1083001-1084000",
  "updated_at": 1765650009727,
  "shows": [
    {
      "id": 1083637,
      "title": "Kantara - A Legend: Chapter 1",
      "type": "movie",
      "year": 2025,
      "end_year": null,
      "poster_url": "https://image.tmdb.org/t/p/w342/zBvw25afDn93embB8L7FzvTT2xq.jpg",
      "backdrop_url": "https://image.tmdb.org/t/p/w780/w57nxiBIODAYHLRs1xmrCY9zEFe.jpg",
      "plot_overview": "During the Kadamba reign, King Vijayendra, the ruler of the fictional feudatory land of Bangra, meets his final fate while venturing into the mystical forest of Kantara. Witnessing this, his son Rajashekara seals the borders of their realm. Later, Prince Kulashekara reopens them through a brutal massacre. The protagonist, Berme, in search of prosperity, crosses the divide and ignites a conflict of faith, power, and destiny between the Kingdom and Nature.",
      "genres": [
        "action",
        "drama",
        "fantasy"
      ],
      "user_rating": 7.0,
      "critic_score": null,
      "us_rating": null,
      "release_date": "2025-10-01",
      "streaming_services": [
        {
          "service_id": 9,
          "service_name": "Prime Video",
          "type": "sub",
          "region": "US"
        }
      ],
      "networks": [],
      "imdb_id": null,
      "tmdb_id": 1083637,
      "relevance_score": 200.006
    }
  ]
}