{
  "range": "117001-118000",
  "updated_at": 1765702770758,
  "shows": [
    {
      "id": 117303,
      "title": "Lessons in Chemistry",
      "type": "tv_series",
      "year": 2023,
      "end_year": null,
      "poster_url": "https://image.tmdb.org/t/p/w342/tCPIf5f6jUIr8KDMWsfaXwXW0kl.jpg",
      "backdrop_url": "https://image.tmdb.org/t/p/w780/cuG3f2l51KdvP9IzBHlol2jR2FC.jpg",
      "plot_overview": "In the 1950s, Elizabeth Zott's dream of being a scientist is challenged by a society that says women belong in the domestic sphere. She accepts a job on a TV cooking show and sets out to teach a nation of overlooked housewives way more than recipes.",
      "genres": [
        "drama"
      ],
      "user_rating": 8.3,
      "critic_score": null,
      "us_rating": null,
      "release_date": "2023-10-12",
      "streaming_services": [
        {
          "service_id": 350,
          "service_name": "Apple TV+",
          "type": "sub",
          "region": "US"
        }
      ],
      "networks": [],
      "imdb_id": null,
      "tmdb_id": 117303,
      "relevance_score": 8.9116
    },
    {
      "id": 117376,
      "title": "Vincenzo",
      "type": "tv_series",
      "year": 2021,
      "end_year": null,
      "poster_url": "https://image.tmdb.org/t/p/w342/dvXJgEDQXhL9Ouot2WkBHpQiHGd.jpg",
      "backdrop_url": "https://image.tmdb.org/t/p/w780/sf7NCqyVUNoyjYuwW5oJke1T1lH.jpg",
      "plot_overview": "At the age of eight, Park Joo Hyeong left for Italy after being adopted. Now an adult, he is known as Vincenzo Cassano and employed by a Mafia family as a consigliere. Due to warring Mafia factions, he flies to South Korea where he gets involved with lawyer Hong Cha Young. She is the type of attorney who will do anything to win a case. Now back in his motherland, he gives an unrivalled conglomerate a taste of his own medicine\u2014with a side of his own version of justice.",
      "genres": [
        "action",
        "comedy",
        "drama"
      ],
      "user_rating": 8.51,
      "critic_score": null,
      "us_rating": null,
      "release_date": "2021-02-20",
      "streaming_services": [
        {
          "service_id": 8,
          "service_name": "Netflix",
          "type": "sub",
          "region": "US"
        }
      ],
      "networks": [],
      "imdb_id": null,
      "tmdb_id": 117376,
      "relevance_score": 13.6124
    },
    {
      "id": 117465,
      "title": "Hell's Paradise",
      "type": "tv_series",
      "year": 2023,
      "end_year": null,
      "poster_url": "https://image.tmdb.org/t/p/w342/1V9I7SvZbYoMbSvdtnlkkq9SB1k.jpg",
      "backdrop_url": "https://image.tmdb.org/t/p/w780/vjiIuR3XGpoGSumQ7DziPAmxIYR.jpg",
      "plot_overview": "For a chance at a pardon, a ninja assassin joins other condemned criminals on a journey to a mysterious island to retrieve an elixir of immortality.",
      "genres": [
        "animation",
        "drama",
        "action",
        "sci-fi"
      ],
      "user_rating": 8.1,
      "critic_score": null,
      "us_rating": null,
      "release_date": "2023-04-01",
      "streaming_services": [
        {
          "service_id": 8,
          "service_name": "Netflix",
          "type": "sub",
          "region": "US"
        }
      ],
      "networks": [],
      "imdb_id": null,
      "tmdb_id": 117465,
      "relevance_score": 10.4612
    },
    {
      "id": 117488,
      "title": "Yellowjackets",
      "type": "tv_series",
      "year": 2021,
      "end_year": null,
      "poster_url": "https://image.tmdb.org/t/p/w342/xRnGrn7Z7SC0KIBodocoU1QgDZF.jpg",
      "backdrop_url": "https://image.tmdb.org/t/p/w780/ibFWJDWS8cTO6s2vZVd2uKDm8p.jpg",
      "plot_overview": "This equal parts survival epic, psychological horror story and coming-of-age drama tells the saga of a team of wildly talented high school girls soccer players who become the (un)lucky survivors of a plane crash deep in the remote northern wilderness. The series chronicles their descent from a complicated but thriving team to savage clans, while also tracking the lives they\u2019ve attempted to piece back together nearly 25 years later.",
      "genres": [
        "drama",
        "mystery"
      ],
      "user_rating": 7.479,
      "critic_score": null,
      "us_rating": null,
      "release_date": "2021-11-14",
      "streaming_services": [
        {
          "service_id": 8,
          "service_name": "Netflix",
          "type": "sub",
          "region": "US"
        }
      ],
      "networks": [],
      "imdb_id": null,
      "tmdb_id": 117488,
      "relevance_score": 14.8525
    },
    {
      "id": 117581,
      "title": "Ginny & Georgia",
      "type": "tv_series",
      "year": 2021,
      "end_year": null,
      "poster_url": "https://image.tmdb.org/t/p/w342/vOwunzW4dx3n0J5mH40n9jTRSwY.jpg",
      "backdrop_url": "https://image.tmdb.org/t/p/w780/lPmUu3xkoksz3xsa1feIUoOBZrg.jpg",
      "plot_overview": "Free-spirited Georgia and her two kids, Ginny and Austin, move north in search of a fresh start but find that the road to new beginnings can be bumpy.",
      "genres": [
        "comedy",
        "drama"
      ],
      "user_rating": 8.049,
      "critic_score": null,
      "us_rating": null,
      "release_date": "2021-02-24",
      "streaming_services": [
        {
          "service_id": 8,
          "service_name": "Netflix",
          "type": "sub",
          "region": "US"
        }
      ],
      "networks": [],
      "imdb_id": null,
      "tmdb_id": 117581,
      "relevance_score": 16.1779
    },
    {
      "id": 117821,
      "title": "WeCrashed",
      "type": "tv_series",
      "year": 2022,
      "end_year": null,
      "poster_url": "https://image.tmdb.org/t/p/w342/rFlYeo84b5YtzNkN0IonN6ZCPic.jpg",
      "backdrop_url": "https://image.tmdb.org/t/p/w780/aQfJ1v9M8mvSSIFydpPd1qeDOV0.jpg",
      "plot_overview": "Inspired by actual events\u2014and the love story at the center of it all. WeWork grew from a single coworking space into a global brand worth $47 billion in under a decade. Then, in less than a year, its valuation dropped $40 billion. What happened?",
      "genres": [
        "drama"
      ],
      "user_rating": 7.3,
      "critic_score": null,
      "us_rating": null,
      "release_date": "2022-03-17",
      "streaming_services": [
        {
          "service_id": 350,
          "service_name": "Apple TV+",
          "type": "sub",
          "region": "US"
        }
      ],
      "networks": [],
      "imdb_id": null,
      "tmdb_id": 117821,
      "relevance_score": 4.9547
    },
    {
      "id": 117830,
      "title": "Tomb Raider: The Legend of Lara Croft",
      "type": "tv_series",
      "year": 2024,
      "end_year": null,
      "poster_url": "https://image.tmdb.org/t/p/w342/1WF982MFHGmsURH13HMQP51Dgr3.jpg",
      "backdrop_url": "https://image.tmdb.org/t/p/w780/zbaUXbBBLmGmHARAVurvUJbIEWt.jpg",
      "plot_overview": "Thrust into a high-stakes chase around the world, fearless adventurer Lara Croft confronts her traumatic past while unraveling an ancient mystery.",
      "genres": [
        "action",
        "animation"
      ],
      "user_rating": 6.3,
      "critic_score": null,
      "us_rating": null,
      "release_date": "2024-10-10",
      "streaming_services": [
        {
          "service_id": 8,
          "service_name": "Netflix",
          "type": "sub",
          "region": "US"
        }
      ],
      "networks": [],
      "imdb_id": null,
      "tmdb_id": 117830,
      "relevance_score": 19.9914
    }
  ]
}