{
  "range": "1370001-1371000",
  "updated_at": 1765651619789,
  "shows": [
    {
      "id": 1370123,
      "title": "A\u00edda y vuelta",
      "type": "movie",
      "year": 2026,
      "end_year": null,
      "poster_url": "https://image.tmdb.org/t/p/w342/a3IvwBXUgse3fzqCngKe0g3xYI9.jpg",
      "backdrop_url": null,
      "plot_overview": "",
      "genres": [
        "comedy"
      ],
      "user_rating": 0.0,
      "critic_score": null,
      "us_rating": null,
      "release_date": "2026-01-30",
      "streaming_services": [
        {
          "service_id": 0,
          "service_name": "Coming Soon",
          "type": "sub",
          "region": "US"
        }
      ],
      "networks": [],
      "imdb_id": null,
      "tmdb_id": 1370123,
      "relevance_score": 0.9839
    },
    {
      "id": 1370814,
      "title": "The Plague",
      "type": "movie",
      "year": 2025,
      "end_year": null,
      "poster_url": "https://image.tmdb.org/t/p/w342/e4aBtGkDgAbwcbT4TxW8kj7yCeq.jpg",
      "backdrop_url": "https://image.tmdb.org/t/p/w780/kHyN3PejjlYWYz1Eah3jS64oV0g.jpg",
      "plot_overview": "A socially awkward tween endures the ruthless hierarchy at a water polo camp, his anxiety spiraling into psychological turmoil over the summer.",
      "genres": [
        "drama",
        "horror"
      ],
      "user_rating": 0.0,
      "critic_score": null,
      "us_rating": null,
      "release_date": "2025-12-24",
      "streaming_services": [
        {
          "service_id": 0,
          "service_name": "Coming Soon",
          "type": "sub",
          "region": "US"
        }
      ],
      "networks": [],
      "imdb_id": null,
      "tmdb_id": 1370814,
      "relevance_score": 2.5663
    }
  ]
}