{
  "range": "1419001-1420000",
  "updated_at": 1765648107515,
  "shows": [
    {
      "id": 1419100,
      "title": "Nem Tudo \u00e9 o que Parece",
      "type": "movie",
      "year": 2025,
      "end_year": null,
      "poster_url": "https://image.tmdb.org/t/p/w342/1btmF8ghn72MAOxp1IeVIuIhQzR.jpg",
      "backdrop_url": null,
      "plot_overview": "",
      "genres": [
        "drama"
      ],
      "user_rating": 0.0,
      "critic_score": null,
      "us_rating": null,
      "release_date": "2025-01-17",
      "streaming_services": [
        {
          "service_id": 531,
          "service_name": "Paramount+",
          "type": "sub",
          "region": "US"
        }
      ],
      "networks": [],
      "imdb_id": null,
      "tmdb_id": 1419100,
      "relevance_score": 0.0
    }
  ]
}