{
  "range": "247001-248000",
  "updated_at": 1765831208809,
  "shows": [
    {
      "id": 247168,
      "title": "Chad Powers",
      "type": "tv_series",
      "year": 2025,
      "poster_url": "https://image.tmdb.org/t/p/w342/wgMS8irQKfMrR6mJhKtK6vbxDTC.jpg",
      "backdrop_url": "https://image.tmdb.org/t/p/w780/lu4HO4kJx2aZzVgjoRcF9vYPaFI.jpg",
      "plot_overview": "Eight years after an unforgivable mistake nukes his promising college football career, hotshot quarterback Russ Holliday tries to resurrect his dreams by disguising himself as Chad Powers - a talented oddball who walks on to the struggling South Georgia Catfish.",
      "genres": [
        "Comedy"
      ],
      "user_rating": 8.2,
      "critic_score": null,
      "us_rating": null,
      "release_date": "2025-09-30",
      "streaming_services": [
        {
          "service_id": 15,
          "service_name": "Hulu",
          "type": "sub",
          "region": "US"
        }
      ],
      "tmdb_id": 247168,
      "production_companies": [
        "Omaha Productions",
        "ESPN",
        "Anomaly Pictures",
        "20th Television",
        "BarnStorm Productions"
      ],
      "networks": [
        "Hulu"
      ],
      "service_name": "Hulu",
      "service_id": 15,
      "prediction_source": "existing",
      "prediction_confidence": 1.0,
      "relevance_score": 103.92
    }
  ]
}