{
  "range": "27001-28000",
  "updated_at": 1765860582474,
  "shows": [
    {
      "id": 27022,
      "title": "The Sorcerer's Apprentice",
      "type": "movie",
      "year": 2010,
      "poster_url": "https://image.tmdb.org/t/p/w342/b5pIUsGll0418NyfNA5eYCI9aoK.jpg",
      "backdrop_url": "https://image.tmdb.org/t/p/w780/mtrfLUfUoQunolDhmQy0GfbRclC.jpg",
      "plot_overview": "Balthazar Blake is a master sorcerer in modern-day Manhattan trying to defend the city from his arch-nemesis, Maxim Horvath. Balthazar can't do it alone, so he recruits Dave Stutler, a seemingly average guy who demonstrates hidden potential, as his reluctant prot\u00e9g\u00e9. The sorcerer gives his unwilling accomplice a crash course in the art and science of magic, and together, these unlikely partners work to stop the forces of darkness.",
      "genres": [],
      "user_rating": 6.135,
      "critic_score": null,
      "us_rating": null,
      "release_date": "2010-07-13",
      "streaming_services": [
        {
          "service_id": 337,
          "service_name": "Disney+",
          "type": "sub",
          "region": "US"
        }
      ],
      "tmdb_id": 27022
    },
    {
      "id": 27205,
      "title": "Inception",
      "type": "movie",
      "year": 2010,
      "poster_url": "https://image.tmdb.org/t/p/w342/xlaY2zyzMfkhk0HSC5VUwzoZPU1.jpg",
      "backdrop_url": "https://image.tmdb.org/t/p/w780/ii8QGacT3MXESqBckQlyrATY0lT.jpg",
      "plot_overview": "Cobb, a skilled thief who commits corporate espionage by infiltrating the subconscious of his targets is offered a chance to regain his old life as payment for a task considered to be impossible: \"inception\", the implantation of another person's idea into a target's subconscious.",
      "genres": [],
      "user_rating": 8.371,
      "critic_score": null,
      "us_rating": null,
      "release_date": "2010-07-15",
      "streaming_services": [
        {
          "service_id": 1899,
          "service_name": "Max",
          "type": "sub",
          "region": "US"
        }
      ],
      "tmdb_id": 27205
    },
    {
      "id": 27374,
      "title": "Lake Mungo",
      "type": "movie",
      "year": 2009,
      "poster_url": "https://image.tmdb.org/t/p/w342/g0zCELYfBfSv8TOGC13buABVN53.jpg",
      "backdrop_url": "https://image.tmdb.org/t/p/w780/5eaS62YjA5Z7WPcf4quyZa5VpeO.jpg",
      "plot_overview": "After 16-year-old Alice Palmer drowns at a local dam, her family experiences a series of strange, inexplicable events centered in and around their home. Unsettled, the Palmers seek the help of a psychic and parapsychologist, who discovers that Alice led a secret, double life. At Lake Mungo, Alice's secret past emerges.",
      "genres": [],
      "user_rating": 6.2,
      "critic_score": null,
      "us_rating": null,
      "release_date": "2009-07-30",
      "streaming_services": [
        {
          "service_id": 9,
          "service_name": "Prime Video",
          "type": "sub",
          "region": "US"
        }
      ],
      "tmdb_id": 27374
    },
    {
      "id": 27578,
      "title": "The Expendables",
      "type": "movie",
      "year": 2010,
      "poster_url": "https://image.tmdb.org/t/p/w342/j09ZkH6R4JWVylBcDai1laCmGw7.jpg",
      "backdrop_url": "https://image.tmdb.org/t/p/w780/sJpbDELfC8VjlRBOOkMJxxWpUg7.jpg",
      "plot_overview": "Barney Ross leads a band of highly skilled mercenaries including knife enthusiast Lee Christmas, a martial arts expert Yin Yang, heavy weapons specialist Hale Caesar, demolitionist Toll Road, and a loose-cannon sniper Gunner Jensen. When the group is commissioned by the mysterious Mr. Church to assassinate the dictator of a small South American island, Barney and Lee visit the remote locale to scout out their opposition and discover the true nature of the conflict engulfing the city.",
      "genres": [],
      "user_rating": 6.247,
      "critic_score": null,
      "us_rating": null,
      "release_date": "2010-08-07",
      "streaming_services": [
        {
          "service_id": 386,
          "service_name": "Peacock",
          "type": "sub",
          "region": "US"
        }
      ],
      "tmdb_id": 27578
    },
    {
      "id": 27581,
      "title": "The Other Guys",
      "type": "movie",
      "year": 2010,
      "poster_url": "https://image.tmdb.org/t/p/w342/wNEHNqo3MgHmj3BUiPSqqq5czcm.jpg",
      "backdrop_url": "https://image.tmdb.org/t/p/w780/imX4Lm6xQYSQdP9C17yqJu4DwEp.jpg",
      "plot_overview": "Unlike their heroic counterparts on the force, desk-bound NYPD detectives Gamble and Hoitz garner no headlines as they work day to day. When a seemingly minor case turns out to be a big deal, the two cops get the opportunity to finally prove to their comrades that they have the right stuff.",
      "genres": [
        "Comedy"
      ],
      "user_rating": 6.319,
      "critic_score": null,
      "us_rating": null,
      "release_date": "2010-08-06",
      "streaming_services": [
        {
          "service_id": 8,
          "service_name": "Netflix",
          "type": "sub",
          "region": "US"
        }
      ],
      "tmdb_id": 27581
    },
    {
      "id": 27945,
      "title": "Hombre",
      "type": "movie",
      "year": 1967,
      "poster_url": "https://image.tmdb.org/t/p/w342/puqgDLxdIZSnodDJ6Q0KxofOebo.jpg",
      "backdrop_url": "https://image.tmdb.org/t/p/w780/wNwE1HpHSTNZE4uIzOZ2AmYkOB1.jpg",
      "plot_overview": "John Russell, disdained by his \"respectable\" fellow stagecoach passengers because he was raised by Indians, becomes their only hope for survival when they are set upon by outlaws.",
      "genres": [
        "Western"
      ],
      "user_rating": 7.0,
      "critic_score": null,
      "us_rating": null,
      "release_date": "1967-03-21",
      "streaming_services": [
        {
          "service_id": 9,
          "service_name": "Prime Video",
          "type": "sub",
          "region": "US"
        }
      ],
      "tmdb_id": 27945
    }
  ]
}