{
  "range": "66001-67000",
  "updated_at": 1765860582487,
  "shows": [
    {
      "id": 66025,
      "title": "Animal Kingdom",
      "type": "tv_series",
      "year": 2016,
      "poster_url": "https://image.tmdb.org/t/p/w342/rzvdKrnSRKPFI0pgqMQknDPpRC9.jpg",
      "backdrop_url": "https://image.tmdb.org/t/p/w780/qTFvZUtNwPz8laW5nYgy9FvKLGP.jpg",
      "plot_overview": "17-year-old Joshua \"J\" Cody moves in with his freewheeling relatives in their Southern California beach town after his mother dies of a heroin overdose. Headed by boot-tough matriarch Janine \"Smurf\" Cody and her right-hand Baz, who runs the business and calls the shots, the clan also consists of Pope, the oldest and most dangerous of the Cody boys; Craig, the tough and fearless middle son; and Deran, the troubled, suspicious \"baby\" of the family.",
      "genres": [
        "Crime",
        "Drama"
      ],
      "user_rating": 7.713,
      "critic_score": null,
      "us_rating": null,
      "release_date": "2016-06-14",
      "streaming_services": [
        {
          "service_id": 8,
          "service_name": "Netflix",
          "type": "sub",
          "region": "US"
        },
        {
          "service_id": 9,
          "service_name": "Prime Video",
          "type": "sub",
          "region": "US"
        }
      ],
      "tmdb_id": 66025
    },
    {
      "id": 66125,
      "title": "Red Dog",
      "type": "movie",
      "year": 2011,
      "poster_url": "https://image.tmdb.org/t/p/w342/cbLh0tVqjqcDnob7w79XkIQ7gGI.jpg",
      "backdrop_url": "https://image.tmdb.org/t/p/w780/wNJAXms3tiKSZ5Q9H5LPa3PkgPA.jpg",
      "plot_overview": "The legendary true story of the Red Dog who united a disparate local community while roaming the Australian outback in search of his long lost master.",
      "genres": [
        "Drama",
        "Comedy",
        "Family"
      ],
      "user_rating": 7.3,
      "critic_score": null,
      "us_rating": null,
      "release_date": "2011-08-04",
      "streaming_services": [
        {
          "service_id": 15,
          "service_name": "Hulu",
          "type": "sub",
          "region": "US"
        },
        {
          "service_id": 9,
          "service_name": "Prime Video",
          "type": "sub",
          "region": "US"
        }
      ],
      "tmdb_id": 66125
    },
    {
      "id": 66276,
      "title": "The Night Of",
      "type": "tv_series",
      "year": 2016,
      "poster_url": "https://image.tmdb.org/t/p/w342/q13XJHdnsmxQL9rXRcnNDrZGHjO.jpg",
      "backdrop_url": "https://image.tmdb.org/t/p/w780/szxeyhCWt7C4hTdq60QYbrslGXn.jpg",
      "plot_overview": "After a night of partying with a female stranger, a man wakes up to find her stabbed to death and is charged with her murder.",
      "genres": [
        "Crime",
        "Drama",
        "Mystery"
      ],
      "user_rating": 7.982,
      "critic_score": null,
      "us_rating": null,
      "release_date": "2016-07-10",
      "streaming_services": [
        {
          "service_id": 1899,
          "service_name": "Max",
          "type": "sub",
          "region": "US"
        }
      ],
      "tmdb_id": 66276
    },
    {
      "id": 66292,
      "title": "Big Little Lies",
      "type": "tv_series",
      "year": 2017,
      "poster_url": "https://image.tmdb.org/t/p/w342/b4HNJOc2N6SGyEhf2RagdpAKBK6.jpg",
      "backdrop_url": "https://image.tmdb.org/t/p/w780/8Wo2Pqjxn7Xmd7p2dxRMIJtyMV7.jpg",
      "plot_overview": "The tale of three mothers of first graders whose apparently perfect lives unravel to the point of murder.",
      "genres": [
        "Drama"
      ],
      "user_rating": 7.888,
      "critic_score": null,
      "us_rating": null,
      "release_date": "2017-02-19",
      "streaming_services": [
        {
          "service_id": 1899,
          "service_name": "Max",
          "type": "sub",
          "region": "US"
        }
      ],
      "tmdb_id": 66292
    },
    {
      "id": 66573,
      "title": "The Good Place",
      "type": "tv_series",
      "year": 2016,
      "poster_url": "https://image.tmdb.org/t/p/w342/qIhsuhoIYR5yTnDta0IL4senbeN.jpg",
      "backdrop_url": "https://image.tmdb.org/t/p/w780/tZmlWeFEMvxrjJhBJJcLNXpSRiG.jpg",
      "plot_overview": "Eleanor Shellstrop, an ordinary woman who, through an extraordinary string of events, enters the afterlife where she comes to realize that she hasn't been a very good person. With the help of her wise afterlife mentor, she's determined to shed her old way of living and discover the awesome (or at least the pretty good) person within.",
      "genres": [
        "Sci-Fi & Fantasy",
        "Comedy"
      ],
      "user_rating": 7.965,
      "critic_score": null,
      "us_rating": null,
      "release_date": "2016-09-19",
      "streaming_services": [
        {
          "service_id": 9,
          "service_name": "Prime Video",
          "type": "sub",
          "region": "US"
        },
        {
          "service_id": 386,
          "service_name": "Peacock",
          "type": "sub",
          "region": "US"
        }
      ],
      "tmdb_id": 66573
    },
    {
      "id": 66732,
      "title": "Stranger Things",
      "type": "tv_series",
      "year": 2016,
      "poster_url": "https://image.tmdb.org/t/p/w342/cVxVGwHce6xnW8UaVUggaPXbmoE.jpg",
      "backdrop_url": "https://image.tmdb.org/t/p/w780/56v2KjBlU4XaOv9rVYEQypROD7P.jpg",
      "plot_overview": "When a young boy vanishes, a small town uncovers a mystery involving secret experiments, terrifying supernatural forces, and one strange little girl.",
      "genres": [
        "Sci-Fi & Fantasy",
        "Mystery",
        "Action & Adventure"
      ],
      "user_rating": 8.598,
      "critic_score": null,
      "us_rating": null,
      "release_date": "2016-07-15",
      "streaming_services": [
        {
          "service_id": 8,
          "service_name": "Netflix",
          "type": "sub",
          "region": "US"
        }
      ],
      "tmdb_id": 66732,
      "is_returning": true,
      "next_season": 5,
      "next_air_date": "2025-12-25",
      "next_episode": 5,
      "relevance_score": 75
    },
    {
      "id": 66786,
      "title": "Timeless",
      "type": "tv_series",
      "year": 2016,
      "poster_url": "https://image.tmdb.org/t/p/w342/wFaS9kROwztTWNxIKBbOLwIgApV.jpg",
      "backdrop_url": "https://image.tmdb.org/t/p/w780/9TvRRh8HUAMK9phVXLInPXHUg6K.jpg",
      "plot_overview": "A mysterious criminal steals a secret state-of-the-art time machine, intent on destroying America as we know it by changing the past. Our only hope is an unexpected team: a scientist, a soldier and a history professor, who must use the machine's prototype to travel back in time to critical events. While they must make every effort not to affect the past themselves, they must also stay one step ahead of this dangerous fugitive. But can this handpicked team uncover the mystery behind it all and en",
      "genres": [
        "Drama",
        "Action & Adventure",
        "Sci-Fi & Fantasy"
      ],
      "user_rating": 7.249,
      "critic_score": null,
      "us_rating": null,
      "release_date": "2016-10-03",
      "streaming_services": [
        {
          "service_id": 9,
          "service_name": "Prime Video",
          "type": "sub",
          "region": "US"
        }
      ],
      "tmdb_id": 66786
    },
    {
      "id": 66788,
      "title": "13 Reasons Why",
      "type": "tv_series",
      "year": 2017,
      "poster_url": "https://image.tmdb.org/t/p/w342/nel144y4dIOdFFid6twN5mAX9Yd.jpg",
      "backdrop_url": "https://image.tmdb.org/t/p/w780/c4CSgKL6QfkJxsWcGYDyTxpbzpW.jpg",
      "plot_overview": "After a teenage girl's perplexing suicide, a classmate receives a series of tapes that unravel the mystery of her tragic choice.",
      "genres": [
        "Drama",
        "Mystery"
      ],
      "user_rating": 7.563,
      "critic_score": null,
      "us_rating": null,
      "release_date": "2017-03-31",
      "streaming_services": [
        {
          "service_id": 8,
          "service_name": "Netflix",
          "type": "sub",
          "region": "US"
        }
      ],
      "tmdb_id": 66788
    },
    {
      "id": 66857,
      "title": "Shooter",
      "type": "tv_series",
      "year": 2016,
      "poster_url": "https://image.tmdb.org/t/p/w342/oMmqtafm6Rdlka1ejJeC9BDWzyO.jpg",
      "backdrop_url": "https://image.tmdb.org/t/p/w780/dyysEEonr5tPcgItlfHItfx5ZCY.jpg",
      "plot_overview": "Bob Lee Swagger is an expert marksman living in exile who is coaxed back into action after learning of a plot to kill the president.",
      "genres": [
        "Action & Adventure",
        "War & Politics",
        "Drama"
      ],
      "user_rating": 7.188,
      "critic_score": null,
      "us_rating": null,
      "release_date": "2016-11-15",
      "streaming_services": [
        {
          "service_id": 9,
          "service_name": "Prime Video",
          "type": "sub",
          "region": "US"
        }
      ],
      "tmdb_id": 66857
    }
  ]
}