{
  "range": "76001-77000",
  "updated_at": 1765702770816,
  "shows": [
    {
      "id": 76122,
      "title": "Marvel One-Shot: The Consultant",
      "type": "movie",
      "year": 2011,
      "end_year": null,
      "poster_url": "https://image.tmdb.org/t/p/w342/xqNLXUUvBnfVk6m3QFGGU0Grgs7.jpg",
      "backdrop_url": "https://image.tmdb.org/t/p/w780/r1Q3jyOpfbF3VDU52w8RzkTPbfe.jpg",
      "plot_overview": "Agent Coulson informs Agent Sitwell that the World Security Council wishes Emil Blonsky to be released from prison to join the Avengers Initiative. As Nick Fury doesn't want to release Blonsky, the two agents decide to send a patsy to sabotage the meeting...",
      "genres": [
        "adventure",
        "fantasy",
        "sci-fi",
        "action"
      ],
      "user_rating": 6.305,
      "critic_score": null,
      "us_rating": null,
      "release_date": "2011-09-13",
      "streaming_services": [
        {
          "service_id": 337,
          "service_name": "Disney+",
          "type": "sub",
          "region": "US"
        }
      ],
      "networks": [],
      "imdb_id": null,
      "tmdb_id": 76122,
      "relevance_score": 8.2545
    },
    {
      "id": 76163,
      "title": "The Expendables 2",
      "type": "movie",
      "year": 2012,
      "end_year": null,
      "poster_url": "https://image.tmdb.org/t/p/w342/74rTIGyGoIu5KSxDVMdr8H3MtMo.jpg",
      "backdrop_url": "https://image.tmdb.org/t/p/w780/ihKsZZYMbyHXC1L7s90WDLITdC5.jpg",
      "plot_overview": "Mr. Church reunites the Expendables for what should be an easy paycheck, but when one of their men is murdered on the job, their quest for revenge puts them deep in enemy territory and up against an unexpected threat.",
      "genres": [
        "action",
        "adventure",
        "thriller"
      ],
      "user_rating": 6.35,
      "critic_score": null,
      "us_rating": null,
      "release_date": "2012-08-08",
      "streaming_services": [
        {
          "service_id": 386,
          "service_name": "Peacock",
          "type": "sub",
          "region": "US"
        }
      ],
      "networks": [],
      "imdb_id": null,
      "tmdb_id": 76163,
      "relevance_score": 10.4845
    },
    {
      "id": 76231,
      "title": "Mayans M.C.",
      "type": "tv_series",
      "year": 2018,
      "end_year": null,
      "poster_url": "https://image.tmdb.org/t/p/w342/510A0upV9WRAynEgs1E2B3eBxi5.jpg",
      "backdrop_url": "https://image.tmdb.org/t/p/w780/bPt7NTQQvrEIBIqwfgWOkjDTIZn.jpg",
      "plot_overview": "Set in the aftermath of Jax Teller\u2019s death, Ezekiel \"EZ\" Reyes is fresh out of prison and a prospect in the Mayans M.C. charter on the Cali/Mexi border. Now, EZ must carve out his new identity in a town where he was once the golden boy with the American Dream in his grasp.",
      "genres": [
        "crime",
        "drama"
      ],
      "user_rating": 8.0,
      "critic_score": null,
      "us_rating": null,
      "release_date": "2018-09-04",
      "streaming_services": [
        {
          "service_id": 337,
          "service_name": "Disney+",
          "type": "sub",
          "region": "US"
        }
      ],
      "networks": [],
      "imdb_id": null,
      "tmdb_id": 76231,
      "relevance_score": 13.481
    },
    {
      "id": 76331,
      "title": "Succession",
      "type": "tv_series",
      "year": 2018,
      "end_year": null,
      "poster_url": "https://image.tmdb.org/t/p/w342/z0XiwdrCQ9yVIr4O0pxzaAYRxdW.jpg",
      "backdrop_url": "https://image.tmdb.org/t/p/w780/bcdUYUFk8GdpZJPiSAas9UeocLH.jpg",
      "plot_overview": "Follow the lives of the Roy family as they contemplate their future once their aging father begins to step back from the media and entertainment conglomerate they control.",
      "genres": [
        "drama",
        "comedy"
      ],
      "user_rating": 8.3,
      "critic_score": null,
      "us_rating": null,
      "release_date": "2018-06-03",
      "streaming_services": [
        {
          "service_id": 1899,
          "service_name": "Max",
          "type": "sub",
          "region": "US"
        }
      ],
      "networks": [],
      "imdb_id": null,
      "tmdb_id": 76331,
      "relevance_score": 23.1841
    },
    {
      "id": 76338,
      "title": "Thor: The Dark World",
      "type": "movie",
      "year": 2013,
      "end_year": null,
      "poster_url": "https://image.tmdb.org/t/p/w342/wp6OxE4poJ4G7c0U2ZIXasTSMR7.jpg",
      "backdrop_url": "https://image.tmdb.org/t/p/w780/4zTsF0RtO0av3YX1NaKDqGKPxYF.jpg",
      "plot_overview": "Thor fights to restore order across the cosmos\u2026 but an ancient race led by the vengeful Malekith returns to plunge the universe back into darkness. Faced with an enemy that even Odin and Asgard cannot withstand, Thor must embark on his most perilous and personal journey yet, one that will reunite him with Jane Foster and force him to sacrifice everything to save us all.",
      "genres": [
        "action",
        "adventure",
        "fantasy"
      ],
      "user_rating": 6.511,
      "critic_score": null,
      "us_rating": null,
      "release_date": "2013-10-30",
      "streaming_services": [
        {
          "service_id": 337,
          "service_name": "Disney+",
          "type": "sub",
          "region": "US"
        }
      ],
      "networks": [],
      "imdb_id": null,
      "tmdb_id": 76338,
      "relevance_score": 8.1929
    },
    {
      "id": 76341,
      "title": "Mad Max: Fury Road",
      "type": "movie",
      "year": 2015,
      "end_year": null,
      "poster_url": "https://image.tmdb.org/t/p/w342/hA2ple9q4qnwxp3hKVNhroipsir.jpg",
      "backdrop_url": "https://image.tmdb.org/t/p/w780/uT895WNwm0aIJRtGizcQhrejWUo.jpg",
      "plot_overview": "An apocalyptic story set in the furthest reaches of our planet, in a stark desert landscape where humanity is broken, and most everyone is crazed fighting for the necessities of life. Within this world exist two rebels on the run who just might be able to restore order.",
      "genres": [
        "action",
        "adventure",
        "sci-fi"
      ],
      "user_rating": 7.628,
      "critic_score": null,
      "us_rating": null,
      "release_date": "2015-05-13",
      "streaming_services": [
        {
          "service_id": 8,
          "service_name": "Netflix",
          "type": "sub",
          "region": "US"
        }
      ],
      "networks": [],
      "imdb_id": null,
      "tmdb_id": 76341,
      "relevance_score": 12.3332
    },
    {
      "id": 76479,
      "title": "The Boys",
      "type": "tv_series",
      "year": 2019,
      "end_year": null,
      "poster_url": "https://image.tmdb.org/t/p/w342/2zmTngn1tYC1AvfnrFLhxeD82hz.jpg",
      "backdrop_url": "https://image.tmdb.org/t/p/w780/7cqKGQMnNabzOpi7qaIgZvQ7NGV.jpg",
      "plot_overview": "A group of vigilantes known informally as \u201cThe Boys\u201d set out to take down corrupt superheroes with no more than blue-collar grit and a willingness to fight dirty.",
      "genres": [
        "sci-fi",
        "action"
      ],
      "user_rating": 8.446,
      "critic_score": null,
      "us_rating": null,
      "release_date": "2019-07-25",
      "streaming_services": [
        {
          "service_id": 9,
          "service_name": "Prime Video",
          "type": "sub",
          "region": "US"
        }
      ],
      "networks": [],
      "imdb_id": null,
      "tmdb_id": 76479,
      "relevance_score": 71.5751
    },
    {
      "id": 76492,
      "title": "Hotel Transylvania",
      "type": "movie",
      "year": 2012,
      "end_year": null,
      "poster_url": "https://image.tmdb.org/t/p/w342/eJGvzGrsfe2sqTUPv5IwLWXjVuR.jpg",
      "backdrop_url": "https://image.tmdb.org/t/p/w780/5rARlA8beRAVXPYzSaF2NoS8Ry5.jpg",
      "plot_overview": "Welcome to Hotel Transylvania, Dracula's lavish five-stake resort, where monsters and their families can live it up and no humans are allowed. One special weekend, Dracula has invited all his best friends to celebrate his beloved daughter Mavis's 118th birthday. For Dracula catering to all of these legendary monsters is no problem but the party really starts when one ordinary guy stumbles into the hotel and changes everything!",
      "genres": [
        "animation",
        "comedy",
        "family",
        "fantasy"
      ],
      "user_rating": 6.963,
      "critic_score": null,
      "us_rating": null,
      "release_date": "2012-09-20",
      "streaming_services": [
        {
          "service_id": 15,
          "service_name": "Hulu",
          "type": "sub",
          "region": "US"
        }
      ],
      "networks": [],
      "imdb_id": null,
      "tmdb_id": 76492,
      "relevance_score": 9.3006
    },
    {
      "id": 76600,
      "title": "Avatar: The Way of Water",
      "type": "movie",
      "year": 2022,
      "end_year": null,
      "poster_url": "https://image.tmdb.org/t/p/w342/t6HIqrRAclMCA60NsSmeqe9RmNV.jpg",
      "backdrop_url": "https://image.tmdb.org/t/p/w780/cd8YDn7M0lfaHhZdU6MvCDxPalP.jpg",
      "plot_overview": "Set more than a decade after the events of the first film, learn the story of the Sully family (Jake, Neytiri, and their kids), the trouble that follows them, the lengths they go to keep each other safe, the battles they fight to stay alive, and the tragedies they endure.",
      "genres": [
        "action",
        "adventure",
        "sci-fi"
      ],
      "user_rating": 7.6,
      "critic_score": null,
      "us_rating": null,
      "release_date": "2022-12-14",
      "streaming_services": [
        {
          "service_id": 337,
          "service_name": "Disney+",
          "type": "sub",
          "region": "US"
        }
      ],
      "networks": [],
      "imdb_id": null,
      "tmdb_id": 76600,
      "relevance_score": 37.3069
    },
    {
      "id": 76669,
      "title": "Elite",
      "type": "tv_series",
      "year": 2018,
      "end_year": null,
      "poster_url": "https://image.tmdb.org/t/p/w342/3NTAbAiao4JLzFQw6YxP1YZppM8.jpg",
      "backdrop_url": "https://image.tmdb.org/t/p/w780/uU6YW3N11qECNfz18LNGAGg3Uir.jpg",
      "plot_overview": "When three working class kids enroll in the most exclusive school in Spain, the clash between the wealthy and the poor students leads to tragedy.",
      "genres": [
        "crime",
        "mystery",
        "drama"
      ],
      "user_rating": 8.018,
      "critic_score": null,
      "us_rating": null,
      "release_date": "2018-10-05",
      "streaming_services": [
        {
          "service_id": 8,
          "service_name": "Netflix",
          "type": "sub",
          "region": "US"
        }
      ],
      "networks": [],
      "imdb_id": null,
      "tmdb_id": 76669,
      "relevance_score": 32.5589
    }
  ]
}