{
  "range": "777001-778000",
  "updated_at": 1765995583399,
  "shows": [
    {
      "id": 777245,
      "title": "Women Talking",
      "type": "movie",
      "year": 2022,
      "poster_url": "https://image.tmdb.org/t/p/w342/wcTc9GveMMjAdHSlzdE0FaRCtqi.jpg",
      "backdrop_url": "https://image.tmdb.org/t/p/w780/edH2sKM63YiSEOWoaJPN87a71dZ.jpg",
      "plot_overview": "A group of women in an isolated religious colony struggle to reconcile their faith with a series of sexual assaults committed by the colony's men.",
      "genres": [
        "Drama"
      ],
      "user_rating": 6.859,
      "critic_score": null,
      "us_rating": null,
      "release_date": "2022-12-23",
      "streaming_services": [
        {
          "service_id": 613,
          "service_name": "Freevee",
          "type": "free",
          "region": "US"
        }
      ],
      "tmdb_id": 777245
    },
    {
      "id": 777443,
      "title": "The Electric State",
      "type": "movie",
      "year": 2025,
      "poster_url": "https://image.tmdb.org/t/p/w342/sI2NiMU8o65hmIMY0JI9CjJ0p7f.jpg",
      "backdrop_url": "https://image.tmdb.org/t/p/w780/2n7lYEeIbucsEQCswRcVB6ZYmMP.jpg",
      "plot_overview": "An orphaned teen hits the road with a mysterious robot to find her long-lost brother, teaming up with a smuggler and his wisecracking sidekick.",
      "genres": [],
      "user_rating": 6.5,
      "critic_score": null,
      "us_rating": null,
      "release_date": "2025-03-07",
      "streaming_services": [
        {
          "service_id": 8,
          "service_name": "Netflix",
          "type": "sub",
          "region": "US"
        }
      ],
      "tmdb_id": 777443
    }
  ]
}