{
  "range": "912001-913000",
  "updated_at": 1765830539743,
  "shows": [
    {
      "id": 912649,
      "title": "Venom: The Last Dance",
      "type": "movie",
      "year": 2024,
      "end_year": null,
      "poster_url": "https://image.tmdb.org/t/p/w342/1RaSkWakWBxxYOWRrqmwo2my5zg.jpg",
      "backdrop_url": "https://image.tmdb.org/t/p/w780/3V4kLQg0kSqPLctI5ziYWabAZYF.jpg",
      "plot_overview": "Eddie and Venom are on the run. Hunted by both of their worlds and with the net closing in, the duo are forced into a devastating decision that will bring the curtains down on Venom and Eddie's last dance.",
      "genres": [
        "action",
        "sci-fi",
        "adventure"
      ],
      "user_rating": 6.673,
      "critic_score": null,
      "us_rating": null,
      "release_date": "2024-10-22",
      "streaming_services": [
        {
          "service_id": 8,
          "service_name": "Netflix",
          "type": "sub",
          "region": "US"
        }
      ],
      "networks": [],
      "imdb_id": null,
      "tmdb_id": 912649,
      "relevance_score": 21.6103
    }
  ]
}